endec/__init__.py
endec/_endec.cpython-312-arm-linux-musleabihf.so
endec/_endec.pyi
endec/exceptions.py
endec/py.typed
endec-0.5.1.dist-info/METADATA
endec-0.5.1.dist-info/WHEEL
endec-0.5.1.dist-info/licenses/LICENSE
endec.libs/libgcc_s-262c4f60.so.1
endec-0.5.1.dist-info/RECORD
