Metadata-Version: 2.4
Name: endec
Version: 0.5.1
Classifier: License :: OSI Approved :: MIT License
Classifier: Intended Audience :: Developers
Classifier: Natural Language :: English
Classifier: Programming Language :: Rust
Classifier: Programming Language :: Python
Classifier: Programming Language :: Python :: 3
Classifier: Programming Language :: Python :: 3 :: Only
Classifier: Programming Language :: Python :: 3.8
Classifier: Programming Language :: Python :: 3.9
Classifier: Programming Language :: Python :: 3.10
Classifier: Programming Language :: Python :: 3.11
Classifier: Programming Language :: Python :: 3.12
Classifier: Programming Language :: Python :: 3.13
Classifier: Programming Language :: Python :: 3.14
Classifier: Programming Language :: Python :: Implementation :: CPython
Classifier: Programming Language :: Python :: Implementation :: PyPy
Classifier: Topic :: Utilities
License-File: LICENSE
Summary: Web-compatible encoding and decoding library
Keywords: encoding_rs,web,codec
Author-email: Thitat Auareesuksakul <flux@thitat.net>
Requires-Python: >=3.8
Project-URL: Changelog, https://github.com/fluxth/endec/releases
Project-URL: Homepage, https://github.com/fluxth/endec
Project-URL: Source, https://github.com/fluxth/endec
